{
	"version": "0.2",
	"ignorePaths": [],
	"dictionaryDefinitions": [],
	"dictionaries": [],
	"words": [
		"Alova",
		"animejs",
		"anticon",
		"Attributify",
		"chanxueyanxietong",
		"fabujishuxuqiu",
		"fabukeyanchengguo",
		"fabulianhecaigouxuqiu",
		"fabuqiyegonggao",
		"gongyinglianxietong",
		"haiwaishichangtuozhan",
		"Iwendazhushou",
		"jiancerenzheng",
		"kolorist",
		"Leafer",
		"leaferjs",
		"luruchannengxinxi",
		"paixu",
		"reactbits",
		"simplebar",
		"Teek",
		"tijiaorenzhengshenqing",
		"uiverse",
		"xiaoxi"
	],
	"ignoreWords": [],
	"import": []
}
